netests/__init__.py
netests/base_cli.py
netests/base_protocols.py
netests/base_run.py
netests/base_selection.py
netests/comparators/__init__.py
netests/comparators/bgp_compare.py
netests/comparators/bgp_up_compare.py
netests/comparators/cdp_compare.py
netests/comparators/facts_compare.py
netests/comparators/lldp_compare.py
netests/comparators/log_compare.py
netests/comparators/ospf_compare.py
netests/comparators/ping_retrieve.py
netests/comparators/vlan_compare.py
netests/comparators/vrf_compare.py
netests/constants.py
netests/converters/__init__.py
netests/converters/bgp/__init__.py
netests/converters/bgp/arista/__init__.py
netests/converters/bgp/arista/api.py
netests/converters/bgp/arista/ssh.py
netests/converters/bgp/cumulus/api.py
netests/converters/bgp/cumulus/ssh.py
netests/converters/bgp/extreme_vsp/ssh.py
netests/converters/bgp/ios/__init__.py
netests/converters/bgp/ios/api.py
netests/converters/bgp/ios/nc.py
netests/converters/bgp/ios/ssh.py
netests/converters/bgp/iosxr/__init__.py
netests/converters/bgp/iosxr/api.py
netests/converters/bgp/iosxr/nc.py
netests/converters/bgp/iosxr/ssh.py
netests/converters/bgp/juniper/__init__.py
netests/converters/bgp/juniper/api.py
netests/converters/bgp/juniper/nc.py
netests/converters/bgp/juniper/ssh.py
netests/converters/bgp/napalm/__init__.py
netests/converters/bgp/napalm/converter.py
netests/converters/bgp/nxos/__init__.py
netests/converters/bgp/nxos/api.py
netests/converters/bgp/nxos/ssh.py
netests/converters/cdp/__init__.py
netests/converters/cdp/cumulus/api.py
netests/converters/cdp/cumulus/ssh.py
netests/converters/cdp/ios/api.py
netests/converters/cdp/ios/nc.py
netests/converters/cdp/ios/ssh.py
netests/converters/cdp/iosxr/ssh.py
netests/converters/cdp/napalm/converter.py
netests/converters/cdp/nxos/api.py
netests/converters/cdp/nxos/nc.py
netests/converters/cdp/nxos/ssh.py
netests/converters/facts/__init__.py
netests/converters/facts/arista/api.py
netests/converters/facts/arista/nc.py
netests-0.3.0.dist-info/entry_points.txt
netests-0.3.0.dist-info/LICENSE
netests-0.3.0.dist-info/WHEEL
netests-0.3.0.dist-info/METADATA
netests-0.3.0.dist-info/RECORD
