Metadata-Version: 2.1
Name: netests
Version: 0.3.0
Summary: Test your Network
Home-page: https://gitlab.com/DylanHamel/netests
License: MIT
Keywords: Netests,Testing,Network,Automation
Author: Dylan Hamel
Author-email: dylan.hamel@protonmail.com
Maintainer: Netests Team
Maintainer-email: ping@netests.io
Requires-Python: >=3.6,<4.0
Classifier: License :: OSI Approved :: MIT License
Classifier: Programming Language :: Python :: 3
Classifier: Programming Language :: Python :: 3.6
Classifier: Programming Language :: Python :: 3.7
Classifier: Programming Language :: Python :: 3.8
Requires-Dist: click (>=7.1.2,<8.0.0)
Requires-Dist: ipaddress (>=1.0.23,<2.0.0)
Requires-Dist: netmiko (>=2.4.2,<3.0.0)
Requires-Dist: nornir (>=2.4.0,<3.0.0)
Requires-Dist: pydantic (>=1.5.1,<2.0.0)
Requires-Dist: pylint (>=2.5.2,<3.0.0)
Requires-Dist: termcolor (>=1.1.0,<2.0.0)
Requires-Dist: typing (>=3.7.4,<4.0.0)
Requires-Dist: xmltodict (>=0.12.0,<0.13.0)
Project-URL: Repository, https://gitlab.com/DylanHamel/netests
